Workbook

Sheet Summary
A1: Reconciliation Summary
A3: Payment status | B3: Enrollments
A4: PAID | B4: =COUNTIF(Reconciliation!$G$6:$G$17,A4) -> 7
A5: PARTIAL | B5: =COUNTIF(Reconciliation!$G$6:$G$17,A5) -> 1
A6: OVERPAID | B6: =COUNTIF(Reconciliation!$G$6:$G$17,A6) -> 1
A7: UNPAID | B7: =COUNTIF(Reconciliation!$G$6:$G$17,A7) -> 3
A8: Total enrollments | B8: =SUM(B4:B7) -> 12
A9: Check: equals rows entered | B9: =IF(B8=COUNTA(Enrollments!$A$6:$A$17),"OK","MISMATCH") -> OK
A11: Money (INR) | B11: Amount
A12: Total fee due (all rows) | B12: =SUM(Reconciliation!$D$6:$D$17) -> 129000
A13: Total collected (all payments) | B13: =SUM(Payments!$D$6:$D$15) -> 99000
A14: Balance still to collect | B14: =SUMIF(Reconciliation!$F$6:$F$17,">0") -> 27000
A15: Overpaid (to refund or adjust) | B15: =-SUMIF(Reconciliation!$F$6:$F$17,"<0") -> 1000
A16: Payments with no enrollment | B16: =SUMIF(Payments!$G$6:$G$15,"NO ENROLLMENT",Payments!$D$6:$D$15) -> 8000
A18: Data issues | B18: Count
A19: Duplicate enrollment rows | B19: =COUNTIF(Reconciliation!$H$6:$H$17,"DUPLICATE ENROLLMENT") -> 2
A20: Missing student names | B20: =COUNTIF(Reconciliation!$H$6:$H$17,"MISSING NAME") -> 1
A21: Payments with no matching enrollment | B21: =COUNTIF(Payments!$G$6:$G$15,"NO ENROLLMENT") -> 1
A23: Note: a duplicate enrollment shares one payment, so its row also shows as paid. Fix duplicates before relying on the per-row status.

Sheet Enrollments
A1: Enrollments (fictional data, typed by hand so it contains typical mistakes)
A5: Enrollment ID | B5: Student ID (as typed) | C5: Student Name | D5: Batch ID | E5: Fee Due (INR)
A6: E001 | B6: S101 | C6: Aarav Sharma | D6: B01 | E6: 12000
A7: E002 | B7: s102 | C7: Diya Patel | D7: B01 | E7: 12000
A8: E003 | B8: S103 | C8: Kabir Singh | D8: B02 | E8: 8000
A9: E004 | B9: S104 | C9: Ishita Rao | D9: B02 | E9: 8000
A10: E005 | B10: S105 | C10: Rahul Verma | D10: B03 | E10: 15000
A11: E006 | B11: S106 | C11: Ananya Iyer | D11: B03 | E11: 15000
A12: E007 | B12: S107 | C12: Vihaan Gupta | D12: B01 | E12: 12000
A13: E008 | B13: S108 | C13: Meera Nair | D13: B04 | E13: 6000
A14: E009 | B14: S101 | C14: Aarav Sharma | D14: B01 | E14: 12000
A15: E010 | B15: S109 | D15: B02 | E15: 8000
A16: E011 | B16: S110 | C16: Aditya Das | D16: B04 | E16: 6000
A17: E012 | B17: S111 | C17: Sara Khan | D17: B03 | E17: 15000

Sheet Payments
A1: Payments (fictional data)
A5: Payment ID | B5: Student ID (as typed) | C5: Batch ID | D5: Amount Paid (INR) | E5: Mode | F5: Clean Key | G5: Match Check
A6: P001 | B6: S101 | C6: B01 | D6: 12000 | E6: UPI | F6: =UPPER(TRIM(B6))&"|"&UPPER(TRIM(C6)) -> S101|B01 | G6: =IF(COUNTIF(Reconciliation!$B$6:$B$17,F6)=0,"NO ENROLLMENT","OK") -> OK
A7: P002 | B7: S102 | C7: B01 | D7: 6000 | E7: UPI | F7: =UPPER(TRIM(B7))&"|"&UPPER(TRIM(C7)) -> S102|B01 | G7: =IF(COUNTIF(Reconciliation!$B$6:$B$17,F7)=0,"NO ENROLLMENT","OK") -> OK
A8: P003 | B8: S102 | C8: B01 | D8: 6000 | E8: Card | F8: =UPPER(TRIM(B8))&"|"&UPPER(TRIM(C8)) -> S102|B01 | G8: =IF(COUNTIF(Reconciliation!$B$6:$B$17,F8)=0,"NO ENROLLMENT","OK") -> OK
A9: P004 | B9: s103 | C9: B02 | D9: 8000 | E9: NetBanking | F9: =UPPER(TRIM(B9))&"|"&UPPER(TRIM(C9)) -> S103|B02 | G9: =IF(COUNTIF(Reconciliation!$B$6:$B$17,F9)=0,"NO ENROLLMENT","OK") -> OK
A10: P005 | B10: S105 | C10: B03 | D10: 10000 | E10: UPI | F10: =UPPER(TRIM(B10))&"|"&UPPER(TRIM(C10)) -> S105|B03 | G10: =IF(COUNTIF(Reconciliation!$B$6:$B$17,F10)=0,"NO ENROLLMENT","OK") -> OK
A11: P006 | B11: S106 | C11: B03 | D11: 16000 | E11: UPI | F11: =UPPER(TRIM(B11))&"|"&UPPER(TRIM(C11)) -> S106|B03 | G11: =IF(COUNTIF(Reconciliation!$B$6:$B$17,F11)=0,"NO ENROLLMENT","OK") -> OK
A12: P007 | B12: S107 | C12: B01 | D12: 12000 | E12: Cash | F12: =UPPER(TRIM(B12))&"|"&UPPER(TRIM(C12)) -> S107|B01 | G12: =IF(COUNTIF(Reconciliation!$B$6:$B$17,F12)=0,"NO ENROLLMENT","OK") -> OK
A13: P008 | B13: S108 | C13: B04 | D13: 6000 | E13: UPI | F13: =UPPER(TRIM(B13))&"|"&UPPER(TRIM(C13)) -> S108|B04 | G13: =IF(COUNTIF(Reconciliation!$B$6:$B$17,F13)=0,"NO ENROLLMENT","OK") -> OK
A14: P009 | B14: S120 | C14: B02 | D14: 8000 | E14: UPI | F14: =UPPER(TRIM(B14))&"|"&UPPER(TRIM(C14)) -> S120|B02 | G14: =IF(COUNTIF(Reconciliation!$B$6:$B$17,F14)=0,"NO ENROLLMENT","OK") -> NO ENROLLMENT
A15: P010 | B15: S111 | C15: B03 | D15: 15000 | E15: Card | F15: =UPPER(TRIM(B15))&"|"&UPPER(TRIM(C15)) -> S111|B03 | G15: =IF(COUNTIF(Reconciliation!$B$6:$B$17,F15)=0,"NO ENROLLMENT","OK") -> OK

Sheet Reconciliation
A1: Reconciliation: each enrollment compared with the payments received
A2: Clean Key = student ID and batch ID with spaces removed and capital letters, so S102 and s102 match.
A5: Enrollment ID | B5: Clean Key | C5: Student Name | D5: Fee Due | E5: Paid | F5: Balance | G5: Payment Status | H5: Data Check
A6: =Enrollments!A6 -> E001 | B6: =UPPER(TRIM(Enrollments!B6))&"|"&UPPER(TRIM(Enrollments!D6)) -> S101|B01 | C6: =Enrollments!C6&"" -> Aarav Sharma | D6: =Enrollments!E6 -> 12000 | E6: =SUMIF(Payments!$F$6:$F$15,B6,Payments!$D$6:$D$15) -> 12000 | F6: =D6-E6 -> 0 | G6: =IF(E6=0,"UNPAID",IF(E6<D6,"PARTIAL",IF(E6=D6,"PAID","OVERPAID"))) -> PAID | H6: =IF(COUNTIF($B$6:$B$17,B6)>1,"DUPLICATE ENROLLMENT",IF(TRIM(C6)="","MISSING NAME","OK")) -> DUPLICATE ENROLLMENT
A7: =Enrollments!A7 -> E002 | B7: =UPPER(TRIM(Enrollments!B7))&"|"&UPPER(TRIM(Enrollments!D7)) -> S102|B01 | C7: =Enrollments!C7&"" -> Diya Patel | D7: =Enrollments!E7 -> 12000 | E7: =SUMIF(Payments!$F$6:$F$15,B7,Payments!$D$6:$D$15) -> 12000 | F7: =D7-E7 -> 0 | G7: =IF(E7=0,"UNPAID",IF(E7<D7,"PARTIAL",IF(E7=D7,"PAID","OVERPAID"))) -> PAID | H7: =IF(COUNTIF($B$6:$B$17,B7)>1,"DUPLICATE ENROLLMENT",IF(TRIM(C7)="","MISSING NAME","OK")) -> OK
A8: =Enrollments!A8 -> E003 | B8: =UPPER(TRIM(Enrollments!B8))&"|"&UPPER(TRIM(Enrollments!D8)) -> S103|B02 | C8: =Enrollments!C8&"" -> Kabir Singh | D8: =Enrollments!E8 -> 8000 | E8: =SUMIF(Payments!$F$6:$F$15,B8,Payments!$D$6:$D$15) -> 8000 | F8: =D8-E8 -> 0 | G8: =IF(E8=0,"UNPAID",IF(E8<D8,"PARTIAL",IF(E8=D8,"PAID","OVERPAID"))) -> PAID | H8: =IF(COUNTIF($B$6:$B$17,B8)>1,"DUPLICATE ENROLLMENT",IF(TRIM(C8)="","MISSING NAME","OK")) -> OK
A9: =Enrollments!A9 -> E004 | B9: =UPPER(TRIM(Enrollments!B9))&"|"&UPPER(TRIM(Enrollments!D9)) -> S104|B02 | C9: =Enrollments!C9&"" -> Ishita Rao | D9: =Enrollments!E9 -> 8000 | E9: =SUMIF(Payments!$F$6:$F$15,B9,Payments!$D$6:$D$15) -> 0 | F9: =D9-E9 -> 8000 | G9: =IF(E9=0,"UNPAID",IF(E9<D9,"PARTIAL",IF(E9=D9,"PAID","OVERPAID"))) -> UNPAID | H9: =IF(COUNTIF($B$6:$B$17,B9)>1,"DUPLICATE ENROLLMENT",IF(TRIM(C9)="","MISSING NAME","OK")) -> OK
A10: =Enrollments!A10 -> E005 | B10: =UPPER(TRIM(Enrollments!B10))&"|"&UPPER(TRIM(Enrollments!D10)) -> S105|B03 | C10: =Enrollments!C10&"" -> Rahul Verma | D10: =Enrollments!E10 -> 15000 | E10: =SUMIF(Payments!$F$6:$F$15,B10,Payments!$D$6:$D$15) -> 10000 | F10: =D10-E10 -> 5000 | G10: =IF(E10=0,"UNPAID",IF(E10<D10,"PARTIAL",IF(E10=D10,"PAID","OVERPAID"))) -> PARTIAL | H10: =IF(COUNTIF($B$6:$B$17,B10)>1,"DUPLICATE ENROLLMENT",IF(TRIM(C10)="","MISSING NAME","OK")) -> OK
A11: =Enrollments!A11 -> E006 | B11: =UPPER(TRIM(Enrollments!B11))&"|"&UPPER(TRIM(Enrollments!D11)) -> S106|B03 | C11: =Enrollments!C11&"" -> Ananya Iyer | D11: =Enrollments!E11 -> 15000 | E11: =SUMIF(Payments!$F$6:$F$15,B11,Payments!$D$6:$D$15) -> 16000 | F11: =D11-E11 -> -1000 | G11: =IF(E11=0,"UNPAID",IF(E11<D11,"PARTIAL",IF(E11=D11,"PAID","OVERPAID"))) -> OVERPAID | H11: =IF(COUNTIF($B$6:$B$17,B11)>1,"DUPLICATE ENROLLMENT",IF(TRIM(C11)="","MISSING NAME","OK")) -> OK
A12: =Enrollments!A12 -> E007 | B12: =UPPER(TRIM(Enrollments!B12))&"|"&UPPER(TRIM(Enrollments!D12)) -> S107|B01 | C12: =Enrollments!C12&"" -> Vihaan Gupta | D12: =Enrollments!E12 -> 12000 | E12: =SUMIF(Payments!$F$6:$F$15,B12,Payments!$D$6:$D$15) -> 12000 | F12: =D12-E12 -> 0 | G12: =IF(E12=0,"UNPAID",IF(E12<D12,"PARTIAL",IF(E12=D12,"PAID","OVERPAID"))) -> PAID | H12: =IF(COUNTIF($B$6:$B$17,B12)>1,"DUPLICATE ENROLLMENT",IF(TRIM(C12)="","MISSING NAME","OK")) -> OK
A13: =Enrollments!A13 -> E008 | B13: =UPPER(TRIM(Enrollments!B13))&"|"&UPPER(TRIM(Enrollments!D13)) -> S108|B04 | C13: =Enrollments!C13&"" -> Meera Nair | D13: =Enrollments!E13 -> 6000 | E13: =SUMIF(Payments!$F$6:$F$15,B13,Payments!$D$6:$D$15) -> 6000 | F13: =D13-E13 -> 0 | G13: =IF(E13=0,"UNPAID",IF(E13<D13,"PARTIAL",IF(E13=D13,"PAID","OVERPAID"))) -> PAID | H13: =IF(COUNTIF($B$6:$B$17,B13)>1,"DUPLICATE ENROLLMENT",IF(TRIM(C13)="","MISSING NAME","OK")) -> OK
A14: =Enrollments!A14 -> E009 | B14: =UPPER(TRIM(Enrollments!B14))&"|"&UPPER(TRIM(Enrollments!D14)) -> S101|B01 | C14: =Enrollments!C14&"" -> Aarav Sharma | D14: =Enrollments!E14 -> 12000 | E14: =SUMIF(Payments!$F$6:$F$15,B14,Payments!$D$6:$D$15) -> 12000 | F14: =D14-E14 -> 0 | G14: =IF(E14=0,"UNPAID",IF(E14<D14,"PARTIAL",IF(E14=D14,"PAID","OVERPAID"))) -> PAID | H14: =IF(COUNTIF($B$6:$B$17,B14)>1,"DUPLICATE ENROLLMENT",IF(TRIM(C14)="","MISSING NAME","OK")) -> DUPLICATE ENROLLMENT
A15: =Enrollments!A15 -> E010 | B15: =UPPER(TRIM(Enrollments!B15))&"|"&UPPER(TRIM(Enrollments!D15)) -> S109|B02 | C15: =Enrollments!C15&"" | D15: =Enrollments!E15 -> 8000 | E15: =SUMIF(Payments!$F$6:$F$15,B15,Payments!$D$6:$D$15) -> 0 | F15: =D15-E15 -> 8000 | G15: =IF(E15=0,"UNPAID",IF(E15<D15,"PARTIAL",IF(E15=D15,"PAID","OVERPAID"))) -> UNPAID | H15: =IF(COUNTIF($B$6:$B$17,B15)>1,"DUPLICATE ENROLLMENT",IF(TRIM(C15)="","MISSING NAME","OK")) -> MISSING NAME
A16: =Enrollments!A16 -> E011 | B16: =UPPER(TRIM(Enrollments!B16))&"|"&UPPER(TRIM(Enrollments!D16)) -> S110|B04 | C16: =Enrollments!C16&"" -> Aditya Das | D16: =Enrollments!E16 -> 6000 | E16: =SUMIF(Payments!$F$6:$F$15,B16,Payments!$D$6:$D$15) -> 0 | F16: =D16-E16 -> 6000 | G16: =IF(E16=0,"UNPAID",IF(E16<D16,"PARTIAL",IF(E16=D16,"PAID","OVERPAID"))) -> UNPAID | H16: =IF(COUNTIF($B$6:$B$17,B16)>1,"DUPLICATE ENROLLMENT",IF(TRIM(C16)="","MISSING NAME","OK")) -> OK
A17: =Enrollments!A17 -> E012 | B17: =UPPER(TRIM(Enrollments!B17))&"|"&UPPER(TRIM(Enrollments!D17)) -> S111|B03 | C17: =Enrollments!C17&"" -> Sara Khan | D17: =Enrollments!E17 -> 15000 | E17: =SUMIF(Payments!$F$6:$F$15,B17,Payments!$D$6:$D$15) -> 15000 | F17: =D17-E17 -> 0 | G17: =IF(E17=0,"UNPAID",IF(E17<D17,"PARTIAL",IF(E17=D17,"PAID","OVERPAID"))) -> PAID | H17: =IF(COUNTIF($B$6:$B$17,B17)>1,"DUPLICATE ENROLLMENT",IF(TRIM(C17)="","MISSING NAME","OK")) -> OK
